openbabel/openbabel.py
openbabel/__init__.py
openbabel/pybel.py
openbabel/_openbabel.so
openbabel/executable.py
openbabel/bin/obrotate
openbabel/bin/obminimize
openbabel/bin/obfitall
openbabel/bin/obenergy
openbabel/bin/obtautomer
openbabel/bin/obrms
openbabel/bin/obthermo
openbabel/bin/roundtrip
openbabel/bin/obfit
openbabel/bin/obrotamer
openbabel/bin/obprop
openbabel/bin/obsym
openbabel/bin/obprobe
openbabel/bin/obabel
openbabel/bin/obconformer
openbabel/bin/obmm
openbabel/bin/obgrep
openbabel/bin/obgen
openbabel/bin/obspectrophore
openbabel/bin/obdistgen
openbabel/include/inchi/inchi_api.h
openbabel/include/openbabel3/LBFGS.h
openbabel/include/openbabel3/openbabel/generic.h
openbabel/include/openbabel3/openbabel/conformersearch.h
openbabel/include/openbabel3/openbabel/oberror.h
openbabel/include/openbabel3/openbabel/chargemodel.h
openbabel/include/openbabel3/openbabel/chains.h
openbabel/include/openbabel3/openbabel/isomorphism.h
openbabel/include/openbabel3/openbabel/obconversion.h
openbabel/include/openbabel3/openbabel/op.h
openbabel/include/openbabel3/openbabel/chemdrawcdx.h
openbabel/include/openbabel3/openbabel/plugin.h
openbabel/include/openbabel3/openbabel/text.h
openbabel/include/openbabel3/openbabel/groupcontrib.h
openbabel/include/openbabel3/openbabel/dlhandler.h
openbabel/include/openbabel3/openbabel/alias.h
openbabel/include/openbabel3/openbabel/query.h
openbabel/include/openbabel3/openbabel/locale.h
openbabel/include/openbabel3/openbabel/internalcoord.h
openbabel/include/openbabel3/openbabel/optransform.h
openbabel/include/openbabel3/openbabel/babelconfig.h
openbabel/include/openbabel3/openbabel/elements.h
openbabel/include/openbabel3/openbabel/obmolecformat.h
openbabel/include/openbabel3/openbabel/obiter.h
openbabel/include/openbabel3/openbabel/reactionfacade.h
openbabel/include/openbabel3/openbabel/ring.h
openbabel/include/openbabel3/openbabel/data.h
openbabel_wheel-3.1.1.22.dist-info/RECORD
openbabel_wheel-3.1.1.22.dist-info/WHEEL
openbabel_wheel-3.1.1.22.dist-info/entry_points.txt
openbabel_wheel-3.1.1.22.dist-info/METADATA
openbabel_wheel-3.1.1.22.dist-info/licenses/LICENSE
