Metadata-Version: 2.1
Name: openbabel-wheel
Version: 3.1.1.22
Summary: An unofficial repository to distribute OpenBabel prebuilt wheels through Pypi..
Author-Email: Jinzhe Zeng <jinzhe.zeng@rutgers.edu>, Noel O'Boyle <openbabel-discuss@lists.sourceforge.net>
License: 		    GNU GENERAL PUBLIC LICENSE
